agileupbom/__init__.py
agileupbom/cli.py
agileupbom/exceptions.py
agileupbom/paths.py
agileupbom/strings.py
agileupbom/terminal.py
agileupbom-0.0.12.dist-info/entry_points.txt
agileupbom-0.0.12.dist-info/LICENSE
agileupbom-0.0.12.dist-info/WHEEL
agileupbom-0.0.12.dist-info/METADATA
agileupbom-0.0.12.dist-info/RECORD
